esbonio/tutorial.py
esbonio/ext/__init__.py
esbonio/ext/spelling.py
esbonio/relevant_to/__init__.py
esbonio/relevant_to/script.js
esbonio/tutorial_demo/extensions/tutorial/formatting-example.ipynb
esbonio/tutorial_demo/extensions/tutorial/hello-world.ipynb
esbonio/tutorial_demo/extensions/tutorial/solution-example.ipynb
esbonio/tutorial_demo/resources/extensions/tutorial/formatting-example/vscode-screenshot.png
esbonio/tutorial_demo/resources/extensions/tutorial/solution-example/solution-example-soln-01.py
esbonio/tutorial_demo/resources/extensions/tutorial/solution-example/solution-example-soln-02.py
esbonio/tutorial_demo/resources/extensions/tutorial/solution-example/solution-example-soln-03.py
esbonio_extensions-0.2.3.dist-info/METADATA
esbonio_extensions-0.2.3.dist-info/WHEEL
esbonio_extensions-0.2.3.dist-info/licenses/LICENSE
esbonio_extensions-0.2.3.dist-info/RECORD
